README.md
setup.py
runtime_guard/__init__.py
runtime_guard/runtime_guard.py
runtime_guard.egg-info/PKG-INFO
runtime_guard.egg-info/SOURCES.txt
runtime_guard.egg-info/dependency_links.txt
runtime_guard.egg-info/top_level.txt