Metadata-Version: 2.4
Name: runtime_guard
Version: 0.5
Summary: A ressource monitor without any dependencies.
Home-page: https://github.com/M-106/Runtime-Guard
Download-URL: https://github.com/M-106/Runtime-Guard/archive/v_03.tar.gz
Author: Tobia Ippolito
License: MIT
Project-URL: Documentation, https://M-106.github.io/Runtime-Guard/
Project-URL: Source, https://github.com/M-106/Runtime-Guard
Keywords: Training,Monitoring,DeepLearning
Classifier: Programming Language :: Python :: 3
Classifier: Programming Language :: Python :: 3.8
Classifier: Programming Language :: Python :: 3.9
Classifier: Programming Language :: Python :: 3.10
Classifier: Programming Language :: Python :: 3.11
Classifier: Programming Language :: Python :: 3.12
Classifier: Programming Language :: Python :: 3.13
Dynamic: author
Dynamic: classifier
Dynamic: description
Dynamic: description-content-type
Dynamic: download-url
Dynamic: home-page
Dynamic: keywords
Dynamic: license
Dynamic: project-url
Dynamic: summary
